jasmit_firestarter/__init__.py
jasmit_firestarter/auto_update.py
jasmit_firestarter/example.py
jasmit_firestarter/firestarter.py
jasmit_firestarter/std_app.py
jasmit_firestarter/std_logging.py
jasmit_firestarter-0.2.4.dist-info/licenses/LICENSE
jasmit_firestarter-0.2.4.dist-info/METADATA
jasmit_firestarter-0.2.4.dist-info/WHEEL
jasmit_firestarter-0.2.4.dist-info/top_level.txt
jasmit_firestarter-0.2.4.dist-info/RECORD
