Metadata-Version: 2.4
Name: jasmit_firestarter
Version: 0.2.4
Summary: Artifacts often useful when starting a new project. (Fire it up!)
Author-email: jasmit <jasmit@swbell.net>
License-Expression: MIT
Classifier: Programming Language :: Python :: 3
Classifier: Operating System :: OS Independent
Requires-Python: >=3.9
License-File: LICENSE
Dynamic: license-file
